<annotation>
	<folder>images</folder>
	<filename>458.jpg</filename>
	<path>/home/srini/Desktop/images/458.jpg</path>
	<source>
		<database>Unknown</database>
	</source>
	<size>
		<width>1300</width>
		<height>872</height>
		<depth>3</depth>
	</size>
	<segmented>0</segmented>
	<object>
		<name>bison</name>
		<pose>Unspecified</pose>
		<truncated>0</truncated>
		<difficult>0</difficult>
		<bndbox>
			<xmin>657</xmin>
			<ymin>315</ymin>
			<xmax>1204</xmax>
			<ymax>647</ymax>
		</bndbox>
	</object>
	<object>
		<name>bison</name>
		<pose>Unspecified</pose>
		<truncated>0</truncated>
		<difficult>0</difficult>
		<bndbox>
			<xmin>216</xmin>
			<ymin>311</ymin>
			<xmax>727</xmax>
			<ymax>615</ymax>
		</bndbox>
	</object>
</annotation>
