<annotation>
	<folder>images</folder>
	<filename>289.jpg</filename>
	<path>/home/srini/Desktop/images/289.jpg</path>
	<source>
		<database>Unknown</database>
	</source>
	<size>
		<width>2000</width>
		<height>1333</height>
		<depth>3</depth>
	</size>
	<segmented>0</segmented>
	<object>
		<name>Deer</name>
		<pose>Unspecified</pose>
		<truncated>0</truncated>
		<difficult>0</difficult>
		<bndbox>
			<xmin>296</xmin>
			<ymin>199</ymin>
			<xmax>940</xmax>
			<ymax>1261</ymax>
		</bndbox>
	</object>
	<object>
		<name>Deer</name>
		<pose>Unspecified</pose>
		<truncated>0</truncated>
		<difficult>0</difficult>
		<bndbox>
			<xmin>734</xmin>
			<ymin>242</ymin>
			<xmax>1571</xmax>
			<ymax>1192</ymax>
		</bndbox>
	</object>
</annotation>
