<annotation>
	<folder>images</folder>
	<filename>323.jpg</filename>
	<path>/home/srini/Desktop/images/323.jpg</path>
	<source>
		<database>Unknown</database>
	</source>
	<size>
		<width>1280</width>
		<height>720</height>
		<depth>3</depth>
	</size>
	<segmented>0</segmented>
	<object>
		<name>lion</name>
		<pose>Unspecified</pose>
		<truncated>0</truncated>
		<difficult>0</difficult>
		<bndbox>
			<xmin>324</xmin>
			<ymin>376</ymin>
			<xmax>912</xmax>
			<ymax>660</ymax>
		</bndbox>
	</object>
	<object>
		<name>lion</name>
		<pose>Unspecified</pose>
		<truncated>0</truncated>
		<difficult>0</difficult>
		<bndbox>
			<xmin>120</xmin>
			<ymin>204</ymin>
			<xmax>682</xmax>
			<ymax>638</ymax>
		</bndbox>
	</object>
	<object>
		<name>lion</name>
		<pose>Unspecified</pose>
		<truncated>0</truncated>
		<difficult>0</difficult>
		<bndbox>
			<xmin>30</xmin>
			<ymin>234</ymin>
			<xmax>462</xmax>
			<ymax>420</ymax>
		</bndbox>
	</object>
	<object>
		<name>lion</name>
		<pose>Unspecified</pose>
		<truncated>1</truncated>
		<difficult>0</difficult>
		<bndbox>
			<xmin>1</xmin>
			<ymin>324</ymin>
			<xmax>126</xmax>
			<ymax>601</ymax>
		</bndbox>
	</object>
	<object>
		<name>lion</name>
		<pose>Unspecified</pose>
		<truncated>0</truncated>
		<difficult>0</difficult>
		<bndbox>
			<xmin>212</xmin>
			<ymin>86</ymin>
			<xmax>940</xmax>
			<ymax>334</ymax>
		</bndbox>
	</object>
	<object>
		<name>buffalo</name>
		<pose>Unspecified</pose>
		<truncated>0</truncated>
		<difficult>0</difficult>
		<bndbox>
			<xmin>554</xmin>
			<ymin>146</ymin>
			<xmax>1248</xmax>
			<ymax>574</ymax>
		</bndbox>
	</object>
</annotation>
